ezgenesynteny/__init__.py
ezgenesynteny/config.ini
ezgenesynteny/emailaddress.py
ezgenesynteny/genevis.py
ezgenesynteny/getgenes.py
ezgenesynteny/version_check.py
ezgenesynteny-0.0.5.dist-info/LICENSE.txt
ezgenesynteny-0.0.5.dist-info/METADATA
ezgenesynteny-0.0.5.dist-info/WHEEL
ezgenesynteny-0.0.5.dist-info/entry_points.txt
ezgenesynteny-0.0.5.dist-info/top_level.txt
ezgenesynteny-0.0.5.dist-info/RECORD
