Metadata-Version: 2.1
Name: ezgenesynteny
Version: 0.0.5
Summary: A python package to quickly get and visualise the gene order/synteny around a target gene from one or more species.
Home-page: 
Author: Jake Leyhr
Author-email: jakeleyhr535@gmail.com
Classifier: Programming Language :: Python :: 3
Classifier: Operating System :: OS Independent
Requires-Python: >=3.11
License-File: LICENSE.txt
Requires-Dist: requests >=2.31.0
Requires-Dist: packaging
Requires-Dist: biopython >=1.83
Requires-Dist: configparser
Requires-Dist: matplotlib >=3.8.0
Provides-Extra: dev
Requires-Dist: pytest ; extra == 'dev'
Requires-Dist: black ; extra == 'dev'
Requires-Dist: setuptools ; extra == 'dev'
Requires-Dist: twine ; extra == 'dev'
